nio_bot-1.2.1.dist-info/licenses/LICENSE
niobot/__init__.py
niobot/__main__.py
niobot/__version__.py
niobot/_event_stubs.py
niobot/attachment.py
niobot/client.py
niobot/commands.py
niobot/context.py
niobot/exceptions.py
niobot/utils/__init__.py
niobot/utils/checks.py
niobot/utils/federation.py
niobot/utils/help_command.py
niobot/utils/lib.py
niobot/utils/mentions.py
niobot/utils/parsers.py
niobot/utils/string_view.py
niobot/utils/sync_store.py
niobot/utils/typing.py
niobot/utils/unblocking.py
tests/test_attachment.py
tests/test_client.py
tests/test_parsers.py
tests/test_sync_store.py
tests/test_utils_unblocking.py
tests/assets/CREDITS.md
tests/assets/sample-15s.ogg
tests/assets/sample-5s-compressed.mp4
tests/assets/sample-clouds.webp
tests/assets/sample-jpeg.jpg
tests/assets/sample-lipsum-10.txt
tests/assets/syncs/00.json
tests/assets/syncs/01.json
tests/assets/syncs/02.json
nio_bot-1.2.1.dist-info/METADATA
nio_bot-1.2.1.dist-info/WHEEL
nio_bot-1.2.1.dist-info/entry_points.txt
nio_bot-1.2.1.dist-info/top_level.txt
nio_bot-1.2.1.dist-info/RECORD
