Metadata-Version: 2.4
Name: nio-bot
Version: 1.2.1
Summary: Making matrix bots simple
Author-email: Nexus <pip@nexy7574.co.uk>
License: GNU LGPLv3
Project-URL: Source, https://github.com/nexy7574/nio-bot
Project-URL: Tracker, https://github.com/nexy7574/nio-bot/issues
Project-URL: Documentation, https://docs.nio-bot.dev/stable
Project-URL: Matrix Room, https://nio-bot.dev/support
Project-URL: Funding, https://ko-fi.com/nexy7574
Project-URL: Homepage, https://nio-bot.dev
Project-URL: Changelog, https://docs.nio-bot.dev/stable/changelog
Classifier: Development Status :: 5 - Production/Stable
Classifier: Intended Audience :: Developers
Classifier: Natural Language :: English
Classifier: Operating System :: Microsoft :: Windows
Classifier: Operating System :: POSIX
Classifier: Programming Language :: Python :: 3 :: Only
Classifier: Programming Language :: Python :: 3.10
Classifier: Programming Language :: Python :: 3.11
Classifier: Programming Language :: Python :: 3.12
Classifier: Programming Language :: Python :: Implementation :: CPython
Classifier: Topic :: Communications
Classifier: Topic :: Internet
Classifier: Topic :: Software Development :: Libraries
Classifier: Topic :: Software Development :: Libraries :: Application Frameworks
Classifier: Topic :: Utilities
Requires-Python: <3.14,>=3.9
License-File: LICENSE
Requires-Dist: matrix-nio>=0.25.2rc1
Requires-Dist: marko==2.*
Requires-Dist: python-magic~=0.4
Requires-Dist: blurhash-python~=1.2
Requires-Dist: pillow>=9.3.0
Requires-Dist: beautifulsoup4~=4.12
Requires-Dist: pydantic~=2.10
Requires-Dist: aiosqlite~=0.20
Requires-Dist: orjson~=3.10
Provides-Extra: e2ee
Requires-Dist: python-olm; extra == "e2ee"
Requires-Dist: peewee; extra == "e2ee"
Requires-Dist: cachetools; extra == "e2ee"
Requires-Dist: atomicwrites; extra == "e2ee"
Provides-Extra: e2e
Requires-Dist: python-olm; extra == "e2e"
Requires-Dist: peewee; extra == "e2e"
Requires-Dist: cachetools; extra == "e2e"
Requires-Dist: atomicwrites; extra == "e2e"
Provides-Extra: cli
Requires-Dist: httpx>=0.25; extra == "cli"
Requires-Dist: click>=8.1.7; extra == "cli"
Requires-Dist: psutil>=5.9.6; extra == "cli"
Requires-Dist: packaging>=23.1; extra == "cli"
Provides-Extra: dev
Requires-Dist: mkdocs; extra == "dev"
Requires-Dist: mkdocs-material; extra == "dev"
Requires-Dist: black; extra == "dev"
Requires-Dist: mkdocs-autorefs; extra == "dev"
Requires-Dist: mkdocs-glightbox; extra == "dev"
Requires-Dist: mkdocstrings[python]; extra == "dev"
Requires-Dist: mkdocs-git-revision-date-localized-plugin; extra == "dev"
Requires-Dist: isort; extra == "dev"
Requires-Dist: build; extra == "dev"
Requires-Dist: pep440; extra == "dev"
Requires-Dist: pycodestyle; extra == "dev"
Requires-Dist: pytest; extra == "dev"
Requires-Dist: pytest-asyncio; extra == "dev"
Requires-Dist: pytest-benchmark; extra == "dev"
Requires-Dist: pytest-dependency; extra == "dev"
Requires-Dist: ruff; extra == "dev"
Requires-Dist: mike; extra == "dev"
Dynamic: license-file
